parallel_utils/__init__.py
parallel_utils/common/__init__.py
parallel_utils/common/abstract_monitor.py
parallel_utils/process/__init__.py
parallel_utils/process/decorators.py
parallel_utils/process/monitor.py
parallel_utils/process/utils.py
parallel_utils/thread/__init__.py
parallel_utils/thread/decorators.py
parallel_utils/thread/monitor.py
parallel_utils/thread/utils.py
parallel_utils-1.3.1.dist-info/LICENSE
parallel_utils-1.3.1.dist-info/METADATA
parallel_utils-1.3.1.dist-info/WHEEL
parallel_utils-1.3.1.dist-info/top_level.txt
parallel_utils-1.3.1.dist-info/zip-safe
parallel_utils-1.3.1.dist-info/RECORD
