Metadata-Version: 2.1
Name: parallel-utils
Version: 1.3.1
Summary: This library implements a class Monitor, as defined by Per Brinch Hansen and C.A.R. Hoare, for synchronization and concurrent management of threads and processes in Python. It also provides other functions to ease the creation and collection of results for both threads and processes.
Home-page: https://github.com/fernandoenzo/parallel-utils/
Download-URL: https://github.com/fernandoenzo/parallel-utils/
Author: Fernando Enzo Guarini
Author-email: fernandoenzo@gmail.com
License: GPLv3+
Project-URL: Source, https://github.com/fernandoenzo/parallel-utils/
Keywords: concurrency concurrent concurrent-programming distributed library lock locker locker-manager module monitor multiprocess multiprocessing multithreading parallel parallelism process semaphore sync synchronize synchronization thread threading
Classifier: Development Status :: 5 - Production/Stable
Classifier: Intended Audience :: Developers
Classifier: License :: OSI Approved :: GNU General Public License v3 or later (GPLv3+)
Classifier: Operating System :: POSIX
Classifier: Programming Language :: Python :: 3 :: Only
Classifier: Programming Language :: Python :: 3.9
Classifier: Programming Language :: Python :: 3.10
Classifier: Programming Language :: Python :: 3.11
Classifier: Programming Language :: Python :: 3.12
Classifier: Topic :: Software Development :: Libraries :: Python Modules
Requires-Python: >=3.9
License-File: LICENSE
Requires-Dist: private-attrs
